dfm_sentence_trf/__init__.py
dfm_sentence_trf/__main__.py
dfm_sentence_trf/config.py
dfm_sentence_trf/evaluation/task_evaluator.py
dfm_sentence_trf/filtering/cleaning.py
dfm_sentence_trf/hub.py
dfm_sentence_trf/main.py
dfm_sentence_trf/tasks/__init__.py
dfm_sentence_trf/tasks/contrastive.py
dfm_sentence_trf/tasks/cosine_similarity.py
dfm_sentence_trf/tasks/multiplenegativeranking.py
dfm_sentence_trf/tasks/softmax.py
dfm_sentence_trf/tasks/task.py
dfm_sentence_trf/tasks/utils.py
dfm_sentence_trf/training/angle.py
dfm_sentence_trf/training/train.py
dfm_sentence_transformers-0.3.9.dist-info/LICENSE
dfm_sentence_transformers-0.3.9.dist-info/METADATA
dfm_sentence_transformers-0.3.9.dist-info/WHEEL
dfm_sentence_transformers-0.3.9.dist-info/RECORD
