Metadata-Version: 2.1
Name: dfm-sentence-transformers
Version: 0.3.9
Summary: Module for finetuning dfm base-models to sentence transformers
License: MIT
Author: Márton Kardos
Author-email: power.up1163@gmail.com
Requires-Python: >=3.8,<4.0
Classifier: License :: OSI Approved :: MIT License
Classifier: Programming Language :: Python :: 3
Classifier: Programming Language :: Python :: 3.8
Classifier: Programming Language :: Python :: 3.9
Classifier: Programming Language :: Python :: 3.10
Classifier: Programming Language :: Python :: 3.11
Classifier: Programming Language :: Python :: 3.12
Requires-Dist: catalogue (>=2.0.0,<3.0.0)
Requires-Dist: confection (>=0.1.0,<0.2.0)
Requires-Dist: datasets (>=2.14.0,<3.0.0)
Requires-Dist: radicli (>=0.0.25,<0.0.26)
Requires-Dist: scikit-learn (>=1.2.0,<2.0.0)
Requires-Dist: sentence-transformers (>=2.2.0,<3.0.0)
Requires-Dist: torch (>=2.1.0,<3.0.0)
Requires-Dist: tqdm (>=4.63.0,<5.0.0)
